always_note/__init__.py
always_note/note.gif
always_note/note.py
always_note/settings.gif
always_note/settings.py
always_note-0.0.2.dist-info/licenses/LICENSE
always_note-0.0.2.dist-info/METADATA
always_note-0.0.2.dist-info/WHEEL
always_note-0.0.2.dist-info/entry_points.txt
always_note-0.0.2.dist-info/top_level.txt
always_note-0.0.2.dist-info/RECORD
