Metadata-Version: 2.4
Name: always_note
Version: 0.0.2
Summary: An always-on screen note
Author-email: Martin O'Hanlon <martin@ohanlonweb.com>
License-Expression: MIT
Classifier: Programming Language :: Python :: 3
Classifier: Operating System :: OS Independent
Requires-Python: >=3.8
License-File: LICENSE
Requires-Dist: guizero
Dynamic: license-file
